{
  "m_GameObject": {
    "m_FileID": 0,
    "m_PathID": 2427687651032302646
  },
  "m_Enabled": 1,
  "m_Script": {
    "m_FileID": 0,
    "m_PathID": -8501234460252298781
  },
  "m_Name": "",
  "backgroundImage": {
    "m_FileID": 0,
    "m_PathID": 7335950120396915766
  },
  "layoutImage": {
    "m_FileID": 0,
    "m_PathID": 7066719129970017334
  },
  "avatarImage": {
    "m_FileID": 0,
    "m_PathID": 6130186797560562742
  },
  "avatarTransform": {
    "m_FileID": 0,
    "m_PathID": 2231805867931075638
  },
  "usernameText": {
    "m_FileID": 0,
    "m_PathID": 4659619121015948342
  },
  "bioText": {
    "m_FileID": 0,
    "m_PathID": -5100154599949204426
  },
  "border": {
    "m_FileID": 0,
    "m_PathID": 8589570504880423990
  }
}